mother_of_dragons
tests
