Metadata-Version: 2.1
Name: mother-of-dragons
Version: 0.2.8
Summary: Python-based management tool for DragonMint and Innosilicon miners
Home-page: https://github.com/brndnmtthws/mother-of-dragons
Author: Brenden Matthews
Author-email: brenden@diddyinc.com
License: UNKNOWN
Platform: UNKNOWN
Classifier: Programming Language :: Python :: 3
Classifier: License :: OSI Approved :: Apache Software License
Classifier: Operating System :: OS Independent
Requires-Python: >=3.5
Provides-Extra: test
